pyseqlsa/__init__.py
pyseqlsa/__version__.py
pyseqlsa/lsa.py
pyseqlsa/preprosessing.py
pyseqlsa-0.1.3.dist-info/LICENSE
pyseqlsa-0.1.3.dist-info/METADATA
pyseqlsa-0.1.3.dist-info/WHEEL
pyseqlsa-0.1.3.dist-info/top_level.txt
pyseqlsa-0.1.3.dist-info/RECORD
