Metadata-Version: 2.1
Name: pyseqlsa
Version: 0.1.3
Summary: This is lag sequential analysis for python3
Home-page: https://github.com/junlei007/LSA
Author: JunLei D
Author-email: junlei007.love@163.com
License: MIT
Platform: UNKNOWN
Classifier: License :: OSI Approved :: MIT License
Classifier: Programming Language :: Python
Classifier: Programming Language :: Python :: 3
Classifier: Programming Language :: Python :: 3.6
Classifier: Programming Language :: Python :: Implementation :: CPython
Classifier: Programming Language :: Python :: Implementation :: PyPy
Requires-Python: >=3.6.0
Requires-Dist: numpy
Requires-Dist: pandas
